Metadata-Version: 2.4
Name: gdal-utils
Version: 3.12.1.0
Summary: gdal-utils: An extension library for GDAL - Geospatial Data Abstraction Library
Home-page: http://www.gdal.org
Author: Frank Warmerdam
Author-email: warmerdam@pobox.com
Maintainer: Idan Miara
Maintainer-email: idan@miara.com
License: MIT
Classifier: Development Status :: 5 - Production/Stable
Classifier: Intended Audience :: Developers
Classifier: Intended Audience :: Science/Research
Classifier: License :: OSI Approved :: MIT License
Classifier: Operating System :: OS Independent
Classifier: Programming Language :: Python :: 3
Classifier: Topic :: Scientific/Engineering :: GIS
Classifier: Topic :: Scientific/Engineering :: Information Analysis
Requires-Python: >=3.6.0
Requires-Dist: gdal
Provides-Extra: numpy
Requires-Dist: numpy>1.0.0; extra == "numpy"
Dynamic: author
Dynamic: author-email
Dynamic: classifier
Dynamic: description
Dynamic: description-content-type
Dynamic: home-page
Dynamic: license
Dynamic: maintainer
Dynamic: maintainer-email
Dynamic: provides-extra
Dynamic: requires-dist
Dynamic: requires-python
Dynamic: summary
